[
  {
    "filename": "Map Object #14959.txt",
    "name": "Map Object",
    "script_pathid": 39,
    "objectName_parsed": "\u0006",
    "objectName_chinese": "\u0006",
    "objectDescript_parsed": "",
    "objectDescript_chinese": "",
    "effect_parsed": "\"\u0018\u0000\u0000\u0000дёҖжқЎйҳҙжҡ—зҡ„е°Ҹе··гҖӮ\u0016\u0000\u0000\u0000еҜ№иұЎ_йҳҙжҡ—зҡ„е°Ҹе··\u0000\u0000\u0000\u0000\u0000\u0000\u0000\u0000пҝҪ?\u0000\u0000\u0000\u0000\u0000\u0000\u0000\u0000\u0001\u0000\u0000\u0000\u0000\u0000\u0000\u0000\u0000\u0000\u0000\u0000\u0000\u0000\u0000\u0000\u0000\u0000\u0000\u0000\u0001\u0000\u0000\u0000\u0001\u0000\u0000\u0000пҝҪ\u0001\u0000\u0000\u0000\u0000\u0000\u0000",
    "effect_chinese_list": [
      "дёҖжқЎйҳҙжҡ—зҡ„е°Ҹе··гҖӮ",
      "еҜ№иұЎ_йҳҙжҡ—зҡ„е°Ҹе··"
    ]
  },
  {
    "filename": "Map Object #15002.txt",
    "name": "Map Object",
    "script_pathid": 39,
    "objectName_parsed": "\u000f",
    "objectName_chinese": "\u000f",
    "objectDescript_parsed": "",
    "objectDescript_chinese": "",
    "effect_parsed": "",
    "effect_chinese_list": []
  },
  {
    "filename": "Map Object #15008.txt",
    "name": "Map Object",
    "script_pathid": 39,
    "objectName_parsed": "\"",
    "objectName_chinese": "\f",
    "objectDescript_parsed": "",
    "objectDescript_chinese": "",
    "effect_parsed": "",
    "effect_chinese_list": []
  },
  {
    "filename": "Map Object #15012.txt",
    "name": "Map Object",
    "script_pathid": 39,
    "objectName_parsed": "\u0012",
    "objectName_chinese": "\u0012",
    "objectDescript_parsed": "",
    "objectDescript_chinese": "",
    "effect_parsed": "",
    "effect_chinese_list": []
  },
  {
    "filename": "Map Object #15022.txt",
    "name": "Map Object",
    "script_pathid": 39,
    "objectName_parsed": "\u000f",
    "objectName_chinese": "\u000f",
    "objectDescript_parsed": "",
    "objectDescript_chinese": "",
    "effect_parsed": "",
    "effect_chinese_list": []
  },
  {
    "filename": "Map Object #15112.txt",
    "name": "Map Object",
    "script_pathid": 39,
    "objectName_parsed": "\u0006",
    "objectName_chinese": "\u0006",
    "objectDescript_parsed": "",
    "objectDescript_chinese": "",
    "effect_parsed": "\"0\u0000\u0000\u0000жЁӘз©ҝз”°йҮҺзҡ„жІіжөҒпјҢжҳҜжқ‘еӯҗзҡ„жҜҚдәІжІігҖӮ",
    "effect_chinese_list": [
      "жЁӘз©ҝз”°йҮҺзҡ„жІіжөҒпјҢжҳҜжқ‘еӯҗзҡ„жҜҚдәІжІігҖӮ",
      "еҜ№иұЎ_жІіиҫ№"
    ]
  },
  {
    "filename": "Map Object #15121.txt",
    "name": "Map Object",
    "script_pathid": 39,
    "objectName_parsed": "\t",
    "objectName_chinese": "\t",
    "objectDescript_parsed": "",
    "objectDescript_chinese": "",
    "effect_parsed": "",
    "effect_chinese_list": []
  },
  {
    "filename": "Map Object #15233.txt",
    "name": "Map Object",
    "script_pathid": 39,
    "objectName_parsed": "\t",
    "objectName_chinese": "\t",
    "objectDescript_parsed": "",
    "objectDescript_chinese": "",
    "effect_parsed": "",
    "effect_chinese_list": []
  },
  {
    "filename": "Map Object #15288.txt",
    "name": "Map Object",
    "script_pathid": 39,
    "objectName_parsed": "\t",
    "objectName_chinese": "\t",
    "objectDescript_parsed": "",
    "objectDescript_chinese": "",
    "effect_parsed": "",
    "effect_chinese_list": []
  },
  {
    "filename": "Map Object #15384.txt",
    "name": "Map Object",
    "script_pathid": 39,
    "objectName_parsed": "\u000f",
    "objectName_chinese": "\u000f",
    "objectDescript_parsed": "",
    "objectDescript_chinese": "",
    "effect_parsed": "",
    "effect_chinese_list": []
  },
  {
    "filename": "Map Object #15449.txt",
    "name": "Map Object",
    "script_pathid": 39,
    "objectName_parsed": "",
    "objectName_chinese": "",
    "objectDescript_parsed": "еҒҘзҫҺеҶ еҶӣ",
    "objectDescript_chinese": "еҒҘзҫҺеҶ еҶӣ",
    "effect_parsed": "еҠҝеҝ…иҰҒи®©дәәд»¬жҳҺзҷҪиӮҢиӮүзҡ„йӯ”еҠӣзҡ„дәә",
    "effect_chinese_list": []
  },
  {
    "filename": "Map Object #15643.txt",
    "name": "Map Object",
    "script_pathid": 39,
    "objectName_parsed": "",
    "objectName_chinese": "",
    "objectDescript_parsed": "еҘізҘһеғҸ",
    "objectDescript_chinese": "еҘізҘһеғҸ",
    "effect_parsed": "зІҫиҮҙиҖҢе®Ҹдјҹзҡ„еҘізҘһеғҸпјҢжҚ®иҜҙеңЁйҷҚдёҙж—ҘеҪ“еӨ©зҘҲзҘ·зҡ„ж•ҲжһңдјҡжӣҙеҘҪгҖӮ",
    "effect_chinese_list": []
  },
  {
    "filename": "Map Object #15656.txt",
    "name": "Map Object",
    "script_pathid": 39,
    "objectName_parsed": "\t",
    "objectName_chinese": "\t",
    "objectDescript_parsed": "",
    "objectDescript_chinese": "",
    "effect_parsed": "",
    "effect_chinese_list": []
  },
  {
    "filename": "Map Object #15733.txt",
    "name": "Map Object",
    "script_pathid": 39,
    "objectName_parsed": "\"",
    "objectName_chinese": "\f",
    "objectDescript_parsed": "",
    "objectDescript_chinese": "",
    "effect_parsed": "",
    "effect_chinese_list": []
  },
  {
    "filename": "Map Object #15863.txt",
    "name": "Map Object",
    "script_pathid": 39,
    "objectName_parsed": "\u0006",
    "objectName_chinese": "\u0006",
    "objectDescript_parsed": "",
    "objectDescript_chinese": "",
    "effect_parsed": "\"?\u0000\u0000\u0000жқ‘еӯҗзҡ„й©ҝз«ҷпјҢзҺӢеӣҪеҗ„дёӘең°еҢәзҡ„дҝЎд»¶йғҪдјҡеҜ„жқҘиҝҷйҮҢ\u0000",
    "effect_chinese_list": [
      "жқ‘еӯҗзҡ„й©ҝз«ҷпјҢзҺӢеӣҪеҗ„дёӘең°еҢәзҡ„дҝЎд»¶йғҪдјҡеҜ„жқҘиҝҷйҮҢ",
      "\u0000еҜ№иұЎ_й©ҝз«ҷ\u0000\u0000\u0000\u0000\u0000\u0000\u0000\u0000\u0000пҝҪ?\u0000\u0000\u0000\u0000\u0000\u0000\u0000\u0000\u0001\u0000\u0000\u0000\u0000\u0000\u0000\u0000\u0000\u0000\u0000\u0000\u0000\u0000\u0000\u0000\u0000\u0000\u0000\u0000\u0001\u0000\u0000\u0000\u0001\u0000\u0000\u0000пҝҪ\u0002\u0000\u0000\u0000\u0000\u0000\u0000\u0011\u0000\u0000\u0000Condition Checker\u0000\u0000\u0000\u0000\u0000\u0000\u000006\u0000\u0000\u0000\u0000\u0000\u0000\u0000\u0000:пҝҪ\u0000\u0000\u000eпҝҪ\u0003\u0000\u0000\u0000\f\u0000\u0000\u0000InputElement\n\u0000\u0000\u0000OutputTure\u0000\u0000\u000b\u0000\u0000\u0000OutputFalse\u0000\u0003\u0000\u0000\u0000\f\u0000\u0000\u0000InputElement\u0000\u0000\u0000\u000027\u0000\u0000\u0000\u0000\u0000\u0000[\u0000\u0000\u0000System.Boolean, mscorlib, Version=4.0.0.0, Culture=neutral, PublicKeyToken=b77a5c561934e089\u0000\u0001\u0000\u0000\u0000\u0006\u0000\u0000\u0000Output\u0000\u0000\u0000\u0000\u0000\u000075\u0000\u0000\u0000\u0000\u0000\u0000\u0000\u0000\u0000\u0000\u0000\u0000\u0000\u0000\u0000\u0000\u0000\u0000\u0000\u0000\u0000\u0000\u0000\u0000\u0000\u0000\n\u0000\u0000\u0000OutputTure\u0000\u0000\u0000\u0000\u0000\u000027\u0000\u0000\u0000\u0000\u0000\u0000[\u0000\u0000\u0000System.Boolean, mscorlib, Version=4.0.0.0, Culture=neutral, PublicKeyToken=b77a5c561934e089\u0000\u0001\u0000\u0000\u0000\f\u0000\u0000\u0000InputElement\u0000\u0000\u0000\u0000пҝҪ6\u0000\u0000\u0000\u0000\u0000\u0000\u0000\u0000\u0000\u0000\u0001\u0000\u0000\u0000\u0000\u0000\u0000\u0000\u0000\u0000\u0000\u0000\u0000\u0000\u0000\u0000\u000b\u0000\u0000\u0000OutputFalse\u0000\u0000\u0000\u0000\u000027\u0000\u0000\u0000\u0000\u0000\u0000[\u0000\u0000\u0000System.Boolean, mscorlib, Version=4.0.0.0, Culture=neutral, PublicKeyToken=b77a5c561934e089\u0000\u0000\u0000\u0000\u0000\u0001\u0000\u0000\u0000\u0000\u0000\u0000\u0000\u0000\u0000\u0000\u0000\u0000\u0000\u0000\u0000\u0001\u0000\u0000\u0000\u0000\u0000\u0000\u0000\u0000\u0000\u0000\u0000\f\u0000\u0000\u0000Y3BGSO5VFEPL\u0000\u0000\u0000\u0000\u0000\u0000\u0000\u0000\u0000\u0000\u0000\u0000\u0000\u0000\u0000\u0000\u0000\u0000\u0000\u0000\u0004\u0000\u0000\u0000\u0000\u0000\u0000\u0000\f\u0000\u0000\u0000JZ2MSU7GAEIA\u0000\u0000\u0000\u0000\u0001\u0000\u0000\u0000\u0002\u0000\u0000\u0000(\u0000\u0000\u0000жҳҜеҗҰеҠ е…ҘдәҶзҺӢеӣҪе®ЎеҲӨеӣў:еҠ е…ҘдәҶ\u0001\u0000\u0000\u0000\u0000\u0000\u0000\u0000\u0000\u0000\u0000\u0000\u0000\u0000\u0000\u0000\u0000\u0000\u0000\u0000\u0000\u0000\u0000\u0000\u0000\u0000\u0000\u0000\u0000\u0000\u0000\u0000\u0001\u0000\u0000\u0000\u0001\u0000\u0000\u0000пҝҪ\u0001\u0000\u0000\u0000\u0000\u0000\u0000\n\u0000\u0000\u0000Main Event\u0000\u0000\u0000\u0000\u0000\u000076\u0000\u0000\u0000\u0000\u0000\u0000|пҝҪeDпҝҪXbE\u0005\u0000\u0000\u0000\f\u0000\u0000\u0000InputElement\u0007\u0000\u0000\u0000Output1\u0000\u0007\u0000\u0000\u0000Output2\u0000\u0007\u0000\u0000\u0000Output3\u0000\u0007\u0000\u0000\u0000Output4\u0000\u0005\u0000\u0000\u0000\f\u0000\u0000\u0000InputElement\u0000\u0000\u0000\u000037\u0000\u0000\u0000\u0000\u0000\u0000[\u0000\u0000\u0000System.Boolean, mscorlib, Version=4.0.0.0, Culture=neutral, PublicKeyToken=b77a5c561934e089\u0000\u0001\u0000\u0000\u0000\u0007\u0000\u0000\u0000Output2\u0000\u0000\u0000\u0000\u0000пҝҪ8\u0000\u0000\u0000\u0000\u0000\u0000\u0000\u0000\u0000\u0000\u0000\u0000\u0000\u0000\u0000\u0000\u0000\u0000\u0000\u0000\u0000\u0000\u0000\u0000\u0000\u0000\u0007\u0000\u0000\u0000Output1\u0000\u0000\u0000\u0000\u000037\u0000\u0000\u0000\u0000\u0000\u0000[\u0000\u0000\u0000System.Boolean, mscorlib, Version=4.0.0.0, Culture=neutral, PublicKeyToken=b77a5c561934e089\u0000\u0001\u0000\u0000\u0000\f\u0000\u0000\u0000InputElement\u0000\u0000\u0000\u000087\u0000\u0000\u0000\u0000\u0000\u0000\u0000\u0000\u0000\u0000\u0001\u0000\u0000\u0000\u0000\u0000\u0000\u0000\u0000\u0000\u0000\u0000\u0000\u0000\u0000\u0000\u0007\u0000\u0000\u0000Output2\u0000\u0000\u0000\u0000\u000037\u0000\u0000\u0000\u0000\u0000\u0000[\u0000\u0000\u0000System.Boolean, mscorlib, Version=4.0.0.0, Culture=neutral, PublicKeyToken=b77a5c561934e089\u0000\u0001\u0000\u0000\u0000\f\u0000\u0000\u0000InputElement\u0000\u0000\u0000\u0000z8\u0000\u0000\u0000\u0000\u0000\u0000\u0000\u0000\u0000\u0000\u0001\u0000\u0000\u0000\u0000\u0000\u0000\u0000\u0000\u0000\u0000\u0000\u0000\u0000\u0000\u0000\u0007\u0000\u0000\u0000Output3\u0000\u0000\u0000\u0000\u000037\u0000\u0000\u0000\u0000\u0000\u0000[\u0000\u0000\u0000System.Boolean, mscorlib, Version=4.0.0.0, Culture=neutral, PublicKeyToken=b77a5c561934e089\u0000\u0000\u0000\u0000\u0000\u0001\u0000\u0000\u0000\u0000\u0000\u0000\u0000\u0000\u0000\u0000\u0000\u0000\u0000\u0000\u0000\u0007\u0000\u0000\u0000Output4\u0000\u0000\u0000\u0000\u000037\u0000\u0000\u0000\u0000\u0000\u0000[\u0000\u0000\u0000System.Boolean, mscorlib, Version=4.0.0.0, Culture=neutral, PublicKeyToken=b77a5c561934e089\u0000\u0000\u0000\u0000\u0000\u0001\u0000\u0000\u0000\u0000\u0000\u0000\u0000\u0000\u0000\u0000\u0000\u0000\u0000\u0000\u0000\u0001\u0000\u0000\u0000\u0000\u0000\u0000\u0000\u0000\u0000\u0000\u0000\f\u0000\u0000\u0000SWMQD7G3T5OD\u0000\u0000\u0000\u0000\u0000\u0000\u0000\u0000\u0000\u0000\u0000\u0000\u0000\u0000\u0000\u0000\u0000\u0000\u0000\u0000\f\u0000\u0000\u0000SWMQD7G3T5OD\f\u0000\u0000\u0000YU0NGLCS6WCT\u0000\u0000\u0000\u0000\u0000\u0000\u0000\u0000пҝҪ\u0000\u0000\u0000жңүдёҖеӨ©пјҢдҪ йҒҮеҲ°дәҶдёҖдёӘдәҡдәәжү’жүӢпјҢд»–жҠҠдҪ зҡ„й’ұеҢ…з»ҷйЎәиө°еҗҺж’’и…ҝе°ұи·‘гҖӮдәҡдәәзҡ„иә«дҪ“жңәиғҪзү№еҲ«ејәпјҢзһ¬й—ҙе°ұи·‘дәҶеҘҪиҝңпјҢдҪ ж°”дёҚжү“дёҖеӨ„жқҘгҖӮдҪ иҜҘжҖҺд№ҲеҠһпјҹ\u0000\u0000\u0000\u0002\u0000\u0000\u0000\u0000\u0000\u0000\u0000\f\u0000\u0000\u0000Y25G3P97RBN8\u0001\u0000\u0000\u0000\u0000\u0000\u0000\u0000\u000f\u0000\u0000\u0000иө¶зҙ§иҝҪдёҠеҺ»\u0000\u0000\u0000\u0000\u0000\u0000\u0000\u0000\u0000\u0003\u0000\u0000\u0000ж— \u0000\u0000\u0000\u0000\u0000\u0000\u0000\u0000\u0000\u0003\u0000\u0000\u0000ж— \u0000\u0000\u0000\u0000\u0000\f\u0000\u0000\u00004BI0XTDKYTR3\u0001\u0000\u0000\u0000\u0000\u0000\u0000\u0000\u0012\u0000\u0000\u0000дёҠжҠҘз»ҷжІ»е®үе®ҳ\u0000\u0000\u0000\u0000\u0000\u0000\u0000\u0000\u0000\u0000\u0003\u0000\u0000\u0000ж— \u0000\u0000\u0000\u0000\u0000\u0000\u0000\u0000\u0000\u0003\u0000\u0000\u0000ж— \u0000\u0001\u0000\u0000\u0000\u0000\u0000\u0000\u0000\u0000\u0000\u0000\u0000\u0000\u0000\u0000\u0000\u0000\u0000\u0000\u0000\u0000\u0000\u0000\u0000\u0000\u0000\u0000\u0000\u0000\u0000\u0000\u0000\u0000\u0000\u0000\u0000\u0000\u0000\u0000\u0000\u0000\u0000\u0000\u0000\u0001\u0000\u0000\u0000\u0001\u0000\u0000\u0000пҝҪ\u0001\u0000\u0000\u0000\u0000\u0000\u0000\n\u0000\u0000\u0000Main Event\u0000\u0000\u0000\u0000\u0000\u0000-6\u0000\u0000\u0000\u0000\u0000\u0000\u0000пҝҪ&F\u0000@пҝҪпҝҪ\u0005\u0000\u0000\u0000\f\u0000\u0000\u0000InputElement\u0007\u0000\u0000\u0000Output1\u0000\u0007\u0000\u0000\u0000Output2\u0000\u0007\u0000\u0000\u0000Output3\u0000\u0007\u0000\u0000\u0000Output4\u0000\u0005\u0000\u0000\u0000\f\u0000\u0000\u0000InputElement\u0000\u0000\u0000\u000047\u0000\u0000\u0000\u0000\u0000\u0000[\u0000\u0000\u0000System.Boolean, mscorlib, Version=4.0.0.0, Culture=neutral, PublicKeyToken=b77a5c561934e089\u0000\u0003\u0000\u0000\u0000\u0007\u0000\u0000\u0000Output1\u0000\u0000\u0000\u0000\u0000пҝҪ5\u0000\u0000\u0000\u0000\u0000\u0000\u0000\u0000\u0000\u0000\u0007\u0000\u0000\u0000Output1\u0000\u0000\u0000\u0000\u0000пҝҪ5\u0000\u0000\u0000\u0000\u0000\u0000\u0000\u0000\u0000\u0000\u0007\u0000\u0000\u0000Output1\u0000\u0000\u0000\u0000\u0000пҝҪ6\u0000\u0000\u0000\u0000\u0000\u0000\u0000\u0000\u0000\u0000\u0000\u0000\u0000\u0000\u0000\u0000\u0000\u0000\u0000\u0000\u0000\u0000\u0000\u0000\u0000\u0000\u0007\u0000\u0000\u0000Output1\u0000\u0000\u0000\u0000\u000047\u0000\u0000\u0000\u0000\u0000\u0000[\u0000\u0000\u0000System.Boolean, mscorlib, Version=4.0.0.0, Culture=neutral, PublicKeyToken=b77a5c561934e089\u0000\u0001\u0000\u0000\u0000\f\u0000\u0000\u0000InputElement\u0000\u0000\u0000\u0000\u00129\u0000\u0000\u0000\u0000\u0000\u0000\u0000\u0000\u0000\u0000\u0001\u0000\u0000\u0000\u0000\u0000\u0000\u0000\u0000\u0000\u0000\u0000\u0000\u0000\u0000\u0000\u0007\u0000\u0000\u0000Output2\u0000\u0000\u0000\u0000\u000047\u0000\u0000\u0000\u0000\u0000\u0000[\u0000\u0000\u0000System.Boolean, mscorlib, Version=4.0.0.0, Culture=neutral, PublicKeyToken=b77a5c561934e089\u0000\u0000\u0000\u0000\u0000\u0001\u0000\u0000\u0000\u0000\u0000\u0000\u0000\u0000\u0000\u0000\u0000\u0000\u0000\u0000\u0000\u0007\u0000\u0000\u0000Output3\u0000\u0000\u0000\u0000\u000047\u0000\u0000\u0000\u0000\u0000\u0000[\u0000\u0000\u0000System.Boolean, mscorlib, Version=4.0.0.0, Culture=neutral, PublicKeyToken=b77a5c561934e089\u0000\u0000\u0000\u0000\u0000\u0001\u0000\u0000\u0000\u0000\u0000\u0000\u0000\u0000\u0000\u0000\u0000\u0000\u0000\u0000\u0000\u0007\u0000\u0000\u0000Output4\u0000\u0000\u0000\u0000\u000047\u0000\u0000\u0000\u0000\u0000\u0000[\u0000\u0000\u0000System.Boolean, mscorlib, Version=4.0.0.0, Culture=neutral, PublicKeyToken=b77a5c561934e089\u0000\u0000\u0000\u0000\u0000\u0001\u0000\u0000\u0000\u0000\u0000\u0000\u0000\u0000\u0000\u0000\u0000\u0000\u0000\u0000\u0000\u0001\u0000\u0000\u0000\u0000\u0000\u0000\u0000\u0000\u0000\u0000\u0000\f\u0000\u0000\u0000UZ0KGDM3XFNB\u0000\u0000\u0000\u0000\u0000\u0000\u0000\u0000\u0000\u0000\u0000\u0000\u0000\u0000\u0000\u0000\u0000\u0000\u0000\u0000\u0000\u0000\u0000\u0000\f\u0000\u0000\u0000GGBSYSTJY0RC\u0000\u0000\u0000\u0000\u0000\u0000\u0000\u0000>\u0001\u0000\u0000дјҠеҲ©дәҡж–Ҝиў«жҙҫжқҘиҝҷдёӘжқ‘еӯҗ"
    ]
  },
  {
    "filename": "Map Object #15874.txt",
    "name": "Map Object",
    "script_pathid": 39,
    "objectName_parsed": "\u0006",
    "objectName_chinese": "\u0006",
    "objectDescript_parsed": "",
    "objectDescript_chinese": "",
    "effect_parsed": "\"\u001b\u0000\u0000\u0000иҖҒеӯҰиҖ…жүҖеҲӣеҠһзҡ„еӯҰе Ӯ\u0000",
    "effect_chinese_list": [
      "иҖҒеӯҰиҖ…жүҖеҲӣеҠһзҡ„еӯҰе Ӯ",
      "о”ҖлҰҜлҮЁеҫЎк·Ҙо–ҰиҠ \u0000\u0000\u0000\u0000ојҖл¶ҝДҝ\u0000\u0000\u0000ДҖ\u0000\u0000\u0000\u0000\u0000\u0000\u0000\u0000\u0000ДҖ\u0000ДҖ\u0000ојҖл¶ҝ\u0001\u0000\u0000аЁҖ\u0000дҙҖжҘЎвҒ®зҷ…ж№Ҙt\u0000\u0000вҳҖ6\u0000\u0000\u0000лҝҜзҠҪEојҖл¶ҝХғ\u0000а°Җ\u0000дӨҖзҒ®з‘өжұ…жөҘж№ҘЭҙ\u0000дјҖз‘өз•°г…ҙЬҖ\u0000дјҖз‘өз•°гүҙЬҖ\u0000дјҖз‘өз•°гҚҙЬҖ\u0000дјҖз‘өз•°г‘ҙФҖ\u0000а°Җ\u0000дӨҖзҒ®з‘өжұ…жөҘж№Ҙt\u0000гҙҖ7\u0000\u0000е¬Җ\u0000еҢҖзҚ№ж•ҙв№ӯжҪӮжұҜж…Ҙвұ®жҙ жҚізүҜжҘ¬вұўеҳ зүҘжҘіж№ҜгҗҪгҖ®гҖ®гҖ®вҖ¬з•ғз‘¬зүөгөҘж•®з‘өж…Івұ¬еҖ жүөжҘ¬дӯЈзҘҘжҪ”ж•«гө®гқўж„·жҢөгҳөгӨұгҗігҒҘгӨёДҖ\u0000ШҖ\u0000дјҖз‘өз•°t\u0000\u0000бңҖ4\u0000\u0000\u0000\u0000\u0000\u0000\u0000\u0000\u0000\u0000\u0000\u0000ЬҖ\u0000дјҖз‘өз•°г…ҙ\u0000\u0000гҙҖ7\u0000\u0000е¬Җ\u0000еҢҖзҚ№ж•ҙв№ӯжҪӮжұҜж…Ҙвұ®жҙ жҚізүҜжҘ¬вұўеҳ зүҘжҘіж№ҜгҗҪгҖ®гҖ®гҖ®вҖ¬з•ғз‘¬зүөгөҘж•®з‘өж…Івұ¬еҖ жүөжҘ¬дӯЈзҘҘжҪ”ж•«гө®гқўж„·жҢөгҳөгӨұгҗігҒҘгӨёДҖ\u0000а°Җ\u0000дӨҖзҒ®з‘өжұ…жөҘж№Ҙt\u0000еҳҖ7\u0000\u0000\u0000\u0000ДҖ\u0000\u0000\u0000\u0000\u0000\u0000\u0000ЬҖ\u0000дјҖз‘өз•°гүҙ\u0000\u0000гҙҖ7\u0000\u0000е¬Җ\u0000еҢҖзҚ№ж•ҙв№ӯжҪӮжұҜж…Ҙвұ®жҙ жҚізүҜжҘ¬вұўеҳ зүҘжҘіж№ҜгҗҪгҖ®гҖ®гҖ®вҖ¬з•ғз‘¬зүөгөҘж•®з‘өж…Івұ¬еҖ жүөжҘ¬дӯЈзҘҘжҪ”ж•«гө®гқўж„·жҢөгҳөгӨұгҗігҒҘгӨёДҖ\u0000а°Җ\u0000дӨҖзҒ®з‘өжұ…жөҘж№Ҙt\u0000бҖҖ9\u0000\u0000\u0000\u0000ДҖ\u0000\u0000\u0000\u0000\u0000\u0000\u0000ЬҖ\u0000дјҖз‘өз•°гҚҙ\u0000\u0000гҙҖ7\u0000\u0000е¬Җ\u0000еҢҖзҚ№ж•ҙв№ӯжҪӮжұҜж…Ҙвұ®жҙ жҚізүҜжҘ¬вұўеҳ зүҘжҘіж№ҜгҗҪгҖ®гҖ®гҖ®вҖ¬з•ғз‘¬зүөгөҘж•®з‘өж…Івұ¬еҖ жүөжҘ¬дӯЈзҘҘжҪ”ж•«гө®гқўж„·жҢөгҳөгӨұгҗігҒҘгӨё\u0000\u0000ДҖ\u0000\u0000\u0000\u0000\u0000\u0000\u0000ЬҖ\u0000дјҖз‘өз•°г‘ҙ\u0000\u0000гҙҖ7\u0000\u0000е¬Җ\u0000еҢҖзҚ№ж•ҙв№ӯжҪӮжұҜж…Ҙвұ®жҙ жҚізүҜжҘ¬вұўеҳ зүҘжҘіж№ҜгҗҪгҖ®гҖ®гҖ®вҖ¬з•ғз‘¬зүөгөҘж•®з‘өж…Івұ¬еҖ жүөжҘ¬дӯЈзҘҘжҪ”ж•«гө®гқўж„·жҢөгҳөгӨұгҗігҒҘгӨё\u0000\u0000ДҖ\u0000\u0000\u0000\u0000\u0000\u0000\u0000ДҖ\u0000\u0000\u0000\u0000\u0000а°Җ\u0000гҳҖеүғгү—д•’дң¶гЎүO\u0000\u0000\u0000\u0000\u0000\u0000\u0000\u0000\u0000\u0000\u0000\u0000\u0000\u0000\u0000\u0000\u0000ојҖл¶ҝ\u0001о ҖйҰҝк»Ұоҡөлҡ—йҹ©оҫҙиІјл·Өоһ иҫ»лЈҘоһёи®ңиЈҘо’°иӮёлЈӨоҰӘиІҷй“§оһҹи’ҡл“Ёоҡөиҫ—иҸЁо––йӮӯй·ҰоҰҘйӘӘи§Ұо–°иҫӨл“ҰоўӣиҠ’иғЈо’ӮкӮҪйіҰо’¬к–»лЈӨо’әк–»к—Ҙоһ№и’ҡиғҰо–§йӮӯліҜо–Ңй’әкҝЁоҡҘйІһйӣҰо–ӯлӮңи«ҰоһҠлһ”л«ӨоўәйҡғиҝҰо’ҚиӮёкҮ©оҺҝиҠҖи“§оў¶иІҖк“ҘоҡҸй®ҙйӢЁо–Ӯл’ҚлӢҰоҡЎиҰңи«Ҙо’ЁиӮёкіҰоҡЎи®үліҜоҡҢиҫҜлЈӨоҡҖкҶ¬иҸ©о–Ҫи¶ҝиғЁо’җиҡәлЈӨоҡӢк–қиғЈе®Ӯк»Ұоўөл¶җо•қиәҗй·©оҫўиІјл·Өо– йӘӨйӣҰоҡ№йҺүйғҘоҡ¬и¶үйҝ§оҰҘйҺҒлҝЁоўҷйҡғк·Ҙоһҗи’ҡк»Ҙоҡ¶иҫ—йіҘо–ЁиҫӨл“ҰоўӣиҠ’к»Ҙоҡ¶иҫ—йіҰоўҖл¶җк·©оһ„и’ҡйҹҰо–¶йҰҖйӣҰо–ҪлӘҮл«ӨоҡҶл’Ҹи§ҰоҺӢиҠҖлҜӨо–ҺиўҫлғҘоһҸи’ҡйҹҰо–¶йҰҖл—Ёоҫ·иІјк»Ҙоҡ¶иҫ—й«§оҰ„лҫ•л»Ёо–ҲлҶ°лҜ§о’ҷйҡ»лҜӨо–¬йӘ®лЈӨо’ӢиҡәкЈҘо–ғиҺЁл«ӨоҺІиҠҖл·Өо– йһҫйҝ§оўҘйҰҝлЈӨоҡӘиў¶иҮҰо–ҜиәҗліҜо–ҢиҺҝиҹ©оһҢлҰүиЈҘо’«и¶ёйЈҰоҡҜи®»йҮҘоҺіиҠҖл·Өоў к–ҜиғҰо’Һиў№и«Ҙоҫһйҫј\u0000ИҖ\u0000\u0000\u0000а°Җ\u0000г”Җдө„дқ‘г•ҡе”ұдүҒД·\u0000\u0000\u0000б¬Җ\u0000о ҖкҰ®иҸЁо––йӮӯйӣҰо’ӯиҡәлҝЁо’ҷкӘёлҝҘоҡөлҺғДҖ\u0000\u0000\u0000аӨҖ\u0000о”ҖиһӢиі§гӘӣг”¶\u0000\u0000\u0000\u0000\u0000МҖ\u0000оҳҖкӮ—\u0000\u0000а°Җ\u0000гҲҖеҷҡгҚҮдҘҢд°ҙгҘ”ЕҸ\u0000\u0000\u0000в„Җ\u0000о”Җк®Ҳл«Өоһәи’ҡк»Ҙо’¶и®әл§Өо’ҹи¶ёк—ҘоҡҪйҠҸи§Ұо–ӢиӘ•\u0000\u0000\u0000\u0000\u0000МҖ\u0000оҳҖкӮ—\u0000\u0000\u0000\u0000МҖ\u0000оҳҖкӮ—ДҖ\u0000\u0000\u0000\u0000\u0000\u0000\u0000\u0000\u0000\u0000\u0000\u0000\u0000\u0000\u0000\u0000\u0000\u0000\u0000\u0000\u0000ДҖ\u0000ДҖ\u0000ојҖл¶ҝ\u0000\u0000\u0000а°Җ\u0000д”Җж•¶з‘®еҲ зҚҘжұөt\u0000вјҖ6\u0000\u0000\u0000а№ FојҖл¶ҝлҝҜКҪ\u0000а°Җ\u0000дӨҖзҒ®з‘өжұ…жөҘж№ҘЭҙ\u0000дјҖз‘өз•°г…ҙИҖ\u0000а°Җ\u0000дӨҖзҒ®з‘өжұ…жөҘж№Ҙt\u0000гёҖ7\u0000\u0000е¬Җ\u0000еҢҖзҚ№ж•ҙв№ӯжҪӮжұҜж…Ҙвұ®жҙ жҚізүҜжҘ¬вұўеҳ зүҘжҘіж№ҜгҗҪгҖ®гҖ®гҖ®вҖ¬з•ғз‘¬зүөгөҘж•®з‘өж…Івұ¬еҖ жүөжҘ¬дӯЈзҘҘжҪ”ж•«гө®гқўж„·жҢөгҳөгӨұгҗігҒҘгӨёДҖ\u0000ЬҖ\u0000дјҖз‘өз•°г…ҙ\u0000\u0000жёҖ3\u0000\u0000\u0000\u0000\u0000\u0000\u0000\u0000\u0000\u0000\u0000\u0000ЬҖ\u0000дјҖз‘өз•°г…ҙ\u0000\u0000гёҖ7\u0000\u0000е¬Җ\u0000еҢҖзҚ№ж•ҙв№ӯжҪӮжұҜж…Ҙвұ®жҙ жҚізүҜжҘ¬вұўеҳ зүҘжҘіж№ҜгҗҪгҖ®гҖ®гҖ®вҖ¬з•ғз‘¬зүөгөҘж•®з‘өж…Івұ¬еҖ жүөжҘ¬дӯЈзҘҘжҪ”ж•«гө®гқўж„·жҢөгҳөгӨұгҗігҒҘгӨёДҖ\u0000а°Җ\u0000дӨҖзҒ®з‘өжұ…жөҘж№Ҙt\u0000жҳҖ7\u0000\u0000\u0000\u0000ДҖ\u0000\u0000\u0000\u0000\u0000\u0000\u0000ДҖ\u0000\u0000\u0000\u0000\u0000а°Җ\u0000е„Җд‘’еҘҮдЁ°еЁ¶еҲ№H\u0000\u0000\u0000а°Җ\u0000е„Җд‘’еҘҮдЁ°еЁ¶еҲ№аұҲ\u0000дјҖд‘ҷд…ҷе©…г №еҒ…Ф¶\u0000\u0000\u0000ДҖ\u0000г„Җ\u0005о ҖлӘҜкҝЁо–әлҡҘк—Ҙо–¶иӘ‘кҝЁо’үкӮҪліҜоҰҢй’ӯл§Өо–ӢйӮӯйЈҰо–Ҝк’ҸиғЁо–ҒиҶ°и·Ҙо’°к¶ёй«§о–„лҺ…й“©о’®иӮёи»§оҺҜиҠҖлЈӨо–Ҡк’ҸйҹҰоҡ¶йҫңліҜоҰҢй’ӯи»§оўӢк®ўиҹҘоў»к–ҙйғҘоҫҺиІјлӢ§оһҫл–ҒліҜо’ҢлӘәлҮ§оҫ»иІјйҝ§о’®лӘәліҜоўҢйўҝйіҰо’үйӘәл«Өо’әкІ»кҝҘоҰ№й’ӯи»§оҡӢл¶–и«Ҙо’ иҡәліҘо–әкһӨлғҘо–ҒлӮҚиғЈо–Ӯиҡ°к·©оһ”и®Һй«§оһ„л–Ғк·©о–ӮиһҲи§ҘоҡІйӮҲл«ӨоҡҶкӮ—й—Ұо–°иҫ°лҜӨоҫҪиІјлҝЁо’ҷй®әиҮ§оҰөиҠӯліӨоўҡй®ҝи—ҘоўҘкәҪйҜҘоҫһиІјй«©оҡҸлӘңкҝЁоһһйҫ”йіҘо’Ёйҡёй—§о’ҢиӘёиғЈоўӮйҰҝкғҰоҰ·й’ӯи»§о–ӢиҡҲй—ҰоһЈи’ҡиҮ§оҰөиҠӯл»ӨоҰқи’ҷйіҘо’ЁиӮёлЈӨо’ӘкӘёк·©о’”и®№к·Ҙоўҗк®әлЈӨоҫҠиІјйҹҰоҡ й–іиҹ©оҡҚлӮ–иҮЁоҡҡкҠӢліҜо–ҢлҶ°лҜ§о’қи¶ёиҝҘоўҜл¶ғк“ҘоҡҚл®ҙиғЈе®Ӯк»Ұоўөл¶җоққлҡ„иғЁоҫҢиІјл·Ҙо’“и®ёйҝ§о’®лӘәлҹҘоһІиҫ»кҮЁоў°л¶җліҜоһҢләІиҮ§о–өлҠ·лҜ§оўҸиҡҰиҮ§оҫӯиІјл«Өо’ҡлӘәйҹҰо–©лҶ°и§Ұо–ҖкҰүйҹҰо– кӮҮліҜоҰҢй’ӯи»§о–ӢлҠ·лҜ§оҡҸлҡ”йҜ©о–ҶлӮҲл«Өо–ҶкһӨиҸ©о–ЁиҡҲкӢЁо–«иҡҲй—ҰоһЈи’ҡиҮ§оҰөиҠӯліҜо–ҢкӘҸи§Ҙо’©и®ёл«Өоһәл®ұлЈӨоһӯи’ҡк·©о’”и®№к·ҘоҺҗиҠҖиҝҘоўӘиҶҰлЈӨоҡҚк¶–й“Ұо–»и®…л«Өоһәл®ұй«§о–„иәҹй—©оҫҮиІјлҝЁоҡҹкҰ—йіҰо’үиӮёк“Ҙоҫ©иІјк·©оһ”и®ҺиҸЁо–ҪйҫӨй“ҰоҰ¶иҡӣиЈҘоў°лҺ¶к“Ҙоһҹи’ҡиҮ§оҰөиҠӯиғЁоҰҢи¶Үи»§о’°иәәлЈӨоҺ–иҠҖоҷӣл–®йғЁе¶Ҫл·Өоһ кһ»лҜ§оҰӯкә—кҝЁоўәлӘҜк—Ҙо–¶лҡҘк·©о’”и®№к·Ҙо’җиӮёиЈЁо’¬йӘјйіҰо’үиӮ»л§ӨоһҲлҰүл»ҘоҫҒиІјкҝЁоўәлӘҜк—Ҙо–¶лҡҘиЈҘоҡҷиһ‘л«ӨоҡҶиһ‘к“ҘоҫҙиІјиҹҘоһ ләҷл§Ҙоҡҙк–қліҜоўҢйҰҝлЈӨоһҖл’ӣйЈҰо’ҜиӮёлЈӨоўӘйІ°иғЈоҰӮй’ӯи§§о–©кҡӯй—§оҡҢиҰңлЈӨо’ҖкӘёи»ҰоўЁлӘ®ліҜоҰҢкҺӮлғҘоҡұкҫҳк·©о’”и®№к·Ҙо–җиҡ°ліӨоҡҡиҰңкҝҰо–”л®ҜлЈҘо’ёлӘәйҜҰо–ҙлӘјк“Ҙоһ§и’ҡи«ҘоҰӣиҫҮліҜо–Ңлҡ№лЈӨоҰ”й’ӯл§Өо–ӢйӮӯл§ӨоҡҹиҰңиіҘо–әк®ҲліҜоҡҢиҰңл«ӨоҰӣй’ӯл§Өо–ӢйӮӯкӢЁо–«иҡҲиЈҘоһ°и’ҡк·©оһ”и®ҺиҮ§оҰөиҠӯл»Ҙо–Ҳкәҫиҹ©оҫҸиІјйӢҘоҡҢкҺӯлЈҘо’ёлӘәиҹҘо’ иә№йҹҰо– иҠјиғЈоўӮиІҖйіҰо’үй®әк·©о’”и®№к·Ҙоҫҗ"
    ]
  },
  {
    "filename": "Map Object #15948.txt",
    "name": "Map Object",
    "script_pathid": 39,
    "objectName_parsed": "",
    "objectName_chinese": "",
    "objectDescript_parsed": "дҫҸе„’еӯҰиҖ…",
    "objectDescript_chinese": "дҫҸе„’еӯҰиҖ…",
    "effect_parsed": "зҹ®е°Ҹзҡ„дҫҸе„’еӯҰиҖ…пјҢжҲҙзқҖдёҖеүҜзңјй•ңпјҢзңӢиө·жқҘзӣёеҪ“еҚҡеӯҰгҖӮ",
    "effect_chinese_list": []
  },
  {
    "filename": "Map Object #15993.txt",
    "name": "Map Object",
    "script_pathid": 39,
    "objectName_parsed": "",
    "objectName_chinese": "",
    "objectDescript_parsed": "ең°дёӢе®Ө",
    "objectDescript_chinese": "ең°дёӢе®Ө",
    "effect_parsed": "еёёе№ҙиў«й”ҒдёҠзҡ„ең°дёӢе®ӨгҖӮ",
    "effect_chinese_list": []
  },
  {
    "filename": "Map Object #16011.txt",
    "name": "Map Object",
    "script_pathid": 39,
    "objectName_parsed": "",
    "objectName_chinese": "",
    "objectDescript_parsed": "дҪ зҡ„жҲҝй—ҙ",
    "objectDescript_chinese": "дҪ зҡ„жҲҝй—ҙ",
    "effect_parsed": "е°ұжҳҜдҪ зҡ„жҲҝй—ҙгҖӮ",
    "effect_chinese_list": []
  },
  {
    "filename": "Map Object #16068.txt",
    "name": "Map Object",
    "script_pathid": 39,
    "objectName_parsed": "",
    "objectName_chinese": "",
    "objectDescript_parsed": "еҘізҘһеғҸ",
    "objectDescript_chinese": "еҘізҘһеғҸ",
    "effect_parsed": "зІҫиҮҙиҖҢе®Ҹдјҹзҡ„еҘізҘһеғҸпјҢдёҚзҹҘдёәдҪ•пјҢдҪ жҖ»и§үеҫ—еҘізҘһй•ҝеҫ—жңүзӮ№зңјзҶҹгҖӮ",
    "effect_chinese_list": []
  },
  {
    "filename": "Map Object #16169.txt",
    "name": "Map Object",
    "script_pathid": 39,
    "objectName_parsed": "",
    "objectName_chinese": "",
    "objectDescript_parsed": "йҷўеӯҗ",
    "objectDescript_chinese": "йҷўеӯҗ",
    "effect_parsed": "дҪ е®¶зҡ„йҷўеӯҗпјҢз§ҚжңүеҫҲеӨҡзЁҖеҘҮеҸӨжҖӘзҡ„дҪңзү©гҖӮ",
    "effect_chinese_list": []
  },
  {
    "filename": "Map Object #16172.txt",
    "name": "Map Object",
    "script_pathid": 39,
    "objectName_parsed": "\u0006",
    "objectName_chinese": "\u0006",
    "objectDescript_parsed": "",
    "objectDescript_chinese": "",
    "effect_parsed": "\"6\u0000\u0000\u0000жқ‘еӯҗзҡ„й©¬еҺ©пјҢжңүдёҖдәӣжң¬ең°йҘІе…»зҡ„й©¬еҮәе”®гҖӮ\u0000\u0000",
    "effect_chinese_list": [
      "жқ‘еӯҗзҡ„й©¬еҺ©пјҢжңүдёҖдәӣжң¬ең°йҘІе…»зҡ„й©¬еҮәе”®гҖӮ"
    ]
  },
  {
    "filename": "Map Object #16267.txt",
    "name": "Map Object",
    "script_pathid": 39,
    "objectName_parsed": "\"",
    "objectName_chinese": "\f",
    "objectDescript_parsed": "",
    "objectDescript_chinese": "",
    "effect_parsed": "",
    "effect_chinese_list": []
  },
  {
    "filename": "Map Object #16309.txt",
    "name": "Map Object",
    "script_pathid": 39,
    "objectName_parsed": "\u0006",
    "objectName_chinese": "\u0006",
    "objectDescript_parsed": "",
    "objectDescript_chinese": "",
    "effect_parsed": "\"6\u0000\u0000\u0000зғӯй—№зҡ„й…’йҰҶпјҢжҳҜдәәд»¬жңҖе–ңж¬ўзҡ„дј‘й—ІеңәжүҖгҖӮ\u0000\u0000",
    "effect_chinese_list": [
      "зғӯй—№зҡ„й…’йҰҶпјҢжҳҜдәәд»¬жңҖе–ңж¬ўзҡ„дј‘й—ІеңәжүҖгҖӮ"
    ]
  },
  {
    "filename": "Map Object.txt",
    "name": "Map Object",
    "script_pathid": 39,
    "objectName_parsed": "\u0006",
    "objectName_chinese": "\u0006",
    "objectDescript_parsed": "",
    "objectDescript_chinese": "",
    "effect_parsed": "\"\u001b\u0000\u0000\u0000ж•ҷдјҡйҮҢзҘһз§ҳзҡ„зҘһзҲ¶гҖӮ\u0000",
    "effect_chinese_list": [
      "ж•ҷдјҡйҮҢзҘһз§ҳзҡ„зҘһзҲ¶гҖӮ",
      "\u0000еҜ№иҜқ_зҘһзҲ¶\u0000\u0000\u0000\u0000\u0000\u0000\u0000\u0000\u0000пҝҪ?\u0000\u0000\u0000\u0000\u0000\u0000\u0000\u0000\u0000\u0000\u0000\u0000\u0000\u0000\u0000\u0000\u0000\u0000\u0000\u0000\u0000\u0000\u0000\u0000\u0001\u0000\u0000\u0000\u0001\u0000\u0000\u0000пҝҪ\u0000\u0000\u0000\u0000\u0000\u0000\u0000\f\u0000\u0000\u0000Event Result\u0000\u0000\u0000\u000016\u0000\u0000\u0000\u0000\u0000\u0000\u0000пҝҪoE\u0000\u0000пҝҪD\u0002\u0000\u0000\u0000\f\u0000\u0000\u0000InputElement\u0007\u0000\u0000\u0000Output1\u0000\u0002\u0000\u0000\u0000\f\u0000\u0000\u0000InputElement\u0000\u0000\u0000\u0000пҝҪ8\u0000\u0000\u0000\u0000\u0000\u0000[\u0000\u0000\u0000System.Boolean, mscorlib, Version=4.0.0.0, Culture=neutral, PublicKeyToken=b77a5c561934e089\u0000\u0001\u0000\u0000\u0000\u0007\u0000\u0000\u0000Output1\u0000\u0000\u0000\u0000\u0000пҝҪ6\u0000\u0000\u0000\u0000\u0000\u0000\u0000\u0000\u0000\u0000\u0000\u0000\u0000\u0000\u0000\u0000\u0000\u0000\u0000\u0000\u0000\u0000\u0000\u0000\u0000\u0000\u0007\u0000\u0000\u0000Output1\u0000\u0000\u0000\u0000\u0000пҝҪ8\u0000\u0000\u0000\u0000\u0000\u0000[\u0000\u0000\u0000System.Boolean, mscorlib, Version=4.0.0.0, Culture=neutral, PublicKeyToken=b77a5c561934e089\u0000\u0001\u0000\u0000\u0000\f\u0000\u0000\u0000InputElement\u0000\u0000\u0000\u0000пҝҪ8\u0000\u0000\u0000\u0000\u0000\u0000\u0000\u0000\u0000\u0000\u0001\u0000\u0000\u0000\u0000\u0000\u0000\u0000\u0000\u0000\u0000\u0000\u0000\u0000\u0000\u0000\u0001\u0000\u0000\u0000\u0000\u0000\u0000\u0000\u0000\u0000\u0000\u0000\f\u0000\u0000\u00008E6YKAFJG39D\u0000\u0000\u0000\u0000\u0000\u0000\u0000\u0000\f\u0000\u0000\u0000Q2N91H57673K\f\u0000\u0000\u0000X847EE3CN0LN\u0005\u0000\u0000\u0000\u0000\u0000\u0000\u0000\u0001\u0000\u0000\u0000\u000e\u0001\u0000\u0000иҷҪз„¶дҪ д№ҹжғідёәдәәзұ»зҡ„еӯҳдәЎеҮәеҠӣпјҢдҪҶжҳҜдҪ жҳҜдёҚеҸҜиғҪеҠ е…ҘзҺӢеӣҪеҶӣзҡ„гҖӮжҜ•з«ҹеүҚж®өж—¶й—ҙжүҚиў«д»–д»¬жүҖзҫҒжҠјпјҢеңЁд»–д»¬зҡ„и®°еҪ•йҮҢпјҢдҪ еә”иҜҘе·Із»ҸжҳҜдёӘжӯ»дәәдәҶгҖӮеҶөдё”пјҢжҒ¶е…Ҷж°ҙжҷ¶зҡ„е…үи·ҜпјҢиҝҳеңЁеә•йғЁгҖӮиҜҙжҳҺеұһдәҺдҪ зҡ„жҲҳж–—иҝҳжңүеҫҲиҝңгҖӮ\u0000\u0000\u0000\u0000\u0000\u0000\u0000\u0000\u0000\u0000\u0000\u0000\u0000\u0000\u0000\u0000\u0000\u0000\u0000\u0000\u0000\u0000\u0000\u0000\u0000\u0000\u0000\u0000\u0000\u0000\u0001\u0000\u0000\u0000\u0001\u0000\u0000\u0000}\u0002\u0000\u0000\u0000\u0000\u0000\u0000\u000b\u0000\u0000\u0000Chest Event\u0000\u0000\u0000\u0000\u0000!6\u0000\u0000\u0000\u0000\u0000\u0000\u0000\u0000nпҝҪ\u0000\u0000:пҝҪ\u0000\u0000\u0000\u0000\u0000\u0000\u0000\u0000\u0000\u0000\u0000\u0000\u0001\u0000\u0000\u0000\u0004\u0000\u0000\u0000пҝҪ\u0000\u0000\u0000дҪ еңЁйҳҙжҡ—зҡ„зҹҝжҙһдёӯеҸ‘зҺ°дәҶдёҖеӨ„йҡҗи”Ҫзҡ„жҡ—й—ЁгҖӮдҪ з”Ёе°Ҫе…ЁеҠӣжҺЁејҖжҡ—й—ЁпјҢзӮ№дә®з…ӨзҒҜпјҢдҪ еңЁжҡ—й—ЁиғҢеҗҺзҡ„жҲҝй—ҙжүҫеҲ°дәҶдёҖд»¶жҲҳеҲ©е“ҒгҖӮ\u0000\u0000\u0000\u0000\u0000\u0000\u0000\u0000\u0000\u0000\u0000\u0000\u0000\u0000\u0000\u0000\u0001\u0000\u0000\u0000\u0001\u0000\u0000\u0000}\u0002\u0000\u0000\u0000\u0000\u0000\u0000\u000b\u0000\u0000\u0000Chest Event\u0000\u0000\u0000\u0000\u0000\"6\u0000\u0000\u0000\u0000\u0000\u0000\u0000\u0000nпҝҪ\u0000\u0000:пҝҪ\u0000\u0000\u0000\u0000\u0000\u0000\u0000\u0000\u0000\u0000\u0000\u0000\u0001\u0000\u0000\u0000\u0004\u0000\u0000\u0000пҝҪ\u0000\u0000\u0000дҪ еҸ‘зҺ°дәҶдёҖеә§зІҫзҒөзҡ„зҘӯеқӣпјҢзҘӯеқӣдёӯеӨ®ж‘Ҷж”ҫзқҖдёҖд»¶зңӢиө·жқҘеҫҲзІҫзҫҺзҡ„зҸҚе®қгҖӮдҪ и§үеҫ—е®қиҙқж”ҫеңЁиҝҷйҮҢд№ҹдёҚдјҡжңүдәәз”ЁдәҶпјҢдёҚеҰӮдҪ жҠҠе®ғеёҰиө°еҗ§гҖӮ\u0000\u0000\u0000\u0000\u0000\u0000\u0000\u0000\u0000\u0000\u0000\u0000\u0000\u0000\u0000\u0000\u0000\u0001\u0000\u0000\u0000\u0001\u0000\u0000\u0000}\u0002\u0000\u0000\u0000\u0000\u0000\u0000\u000b\u0000\u0000\u0000Chest Event\u0000\u0000\u0000\u0000\u0000#6\u0000\u0000\u0000\u0000\u0000\u0000\u0000\u0000nпҝҪ\u0000\u0000:пҝҪ\u0000\u0000\u0000\u0000\u0000\u0000\u0000\u0000\u0000\u0000\u0000\u0000\u0001\u0000\u0000\u0000\u0004\u0000\u0000\u0000пҝҪ\u0000\u0000\u0000дҪ жқҘеҲ°дёҖеӨ„йҡҗз§ҳд№Ӣең°пјҢиҝҷзүҮеҢәеҹҹж ‘еҸ¶иҢӮеҜҶгҖӮдҪ жӢЁејҖдёҖзүҮзүҮж ‘еҸ¶пјҢеҸ‘зҺ°дәҶдёҖеә§зҘһз§ҳзҡ„еәҹеўҹпјҢеңЁеәҹеўҹйҮҢпјҢдҪ жүҫеҲ°дәҶдёҖд»¶йҒ—зү©гҖӮ\u0000\u0000\u0000\u0000\u0000\u0000\u0000\u0000\u0000\u0000\u0000\u0000\u0000\u0001\u0000\u0000\u0000\u0001\u0000\u0000\u0000}\u0002\u0000\u0000\u0000\u0000\u0000\u0000\u000b\u0000\u0000\u0000Chest Event\u0000\u0000\u0000\u0000\u0000$6\u0000\u0000\u0000\u0000\u0000\u0000\u0000\u0000nпҝҪ\u0000\u0000:пҝҪ\u0000\u0000\u0000\u0000\u0000\u0000\u0000\u0000\u0000\u0000\u0000\u0000\u0001\u0000\u0000\u0000\u0004\u0000\u0000\u0000i\u0000\u0000\u0000дҪ еңЁжӮ¬еҙ–иҫ№еҸ‘зҺ°дәҶдёҖдёӘе®қз®ұпјҢдҪ е……ж»Ўжңҹеҫ…ең°жү“ејҖпјҢеҺҹжқҘйҮҢйқўжҳҜдёҖд»¶дёҚй”ҷзҡ„е®қзү©гҖӮ\u0000\u0000\u0000\u0000\u0000\u0000\u0000\u0000\u0000\u0000\u0000\u0000\u0000\u0000\u0000\u0000\u0000\u0000\u0000\u0001\u0000\u0000\u0000\u0001\u0000\u0000\u0000}\u0002\u0000\u0000\u0000\u0000\u0000\u0000\u000b\u0000\u0000\u0000Chest Event\u0000\u0000\u0000\u0000\u0000%6\u0000\u0000\u0000\u0000\u0000\u0000\u0000\u0000nпҝҪ\u0000\u0000:пҝҪ\u0000\u0000\u0000\u0000\u0000\u0000\u0000\u0000\u0000\u0000\u0000\u0000\u0001\u0000\u0000\u0000\u0004\u0000\u0000\u0000o\u0000\u0000\u0000дҪ еңЁеў“ең°йҮҢеҸ‘зҺ°дәҶдёҖеә§и§„жЁЎдёҚе°Ҹзҡ„еқҹеў“пјҢдҪ иҝӣе…Ҙеқҹеў“йҮҢйқўпјҢжүҫеҲ°дәҶдёҖд»¶дёҚй”ҷзҡ„е®қзү©гҖӮ\u0000\u0000\u0000\u0000\u0000\u0000\u0000\u0000\u0000\u0000\u0000\u0000\u0000\u0001\u0000\u0000\u0000\u0001\u0000\u0000\u0000пҝҪ\u0000\u0000\u0000\u0000\u0000\u0000\u0000\f\u0000\u0000\u0000Event Result\u0000\u0000\u0000\u0000/6\u0000\u0000\u0000\u0000\u0000\u0000\u0000@пҝҪE\u0000@пҝҪE\u0002\u0000\u0000\u0000\f\u0000\u0000\u0000InputElement\u0007\u0000\u0000\u0000Output1\u0000\u0002\u0000\u0000\u0000\f\u0000\u0000\u0000InputElement\u0000\u0000\u0000\u0000пҝҪ8\u0000\u0000\u0000\u0000\u0000\u0000[\u0000\u0000\u0000System.Boolean, mscorlib, Version=4.0.0.0, Culture=neutral, PublicKeyToken=b77a5c561934e089\u0000\u0001\u0000\u0000\u0000\u0007\u0000\u0000\u0000Output1\u0000\u0000\u0000\u0000\u0000:7\u0000\u0000\u0000\u0000\u0000\u0000\u0000\u0000\u0000\u0000\u0000\u0000\u0000\u0000\u0000\u0000\u0000\u0000\u0000\u0000\u0000\u0000\u0000\u0000\u0000\u0000\u0007\u0000\u0000\u0000Output1\u0000\u0000\u0000\u0000\u0000пҝҪ8\u0000\u0000\u0000\u0000\u0000\u0000[\u0000\u0000\u0000System.Boolean, mscorlib, Version=4.0.0.0, Culture=neutral, PublicKeyToken=b77a5c561934e089\u0000\u0001\u0000\u0000\u0000\f\u0000\u0000\u0000InputElement\u0000\u0000\u0000\u0000пҝҪ6\u0000\u0000\u0000\u0000\u0000\u0000\u0000\u0000\u0000\u0000\u0001\u0000\u0000\u0000\u0000\u0000\u0000\u0000\u0000\u0000\u0000\u0000\u0000\u0000\u0000\u0000\u0001\u0000\u0000\u0000\u0000\u0000\u0000\u0000\u0000\u0000\u0000\u0000\f\u0000\u0000\u0000VUZU8Y6VBVNO\u0000\u0000\u0000\u0000\u0000\u0000\u0000\u0000\f\u0000\u0000\u0000TLOCBN2WM77N\f\u0000\u0000\u0000R5YLXGDW5V8L\u0005\u0000\u0000\u0000\u0000\u0000\u0000\u0000\u0001\u0000\u0000\u0000$\u0007\u0000\u0000дҪ й—®еӨҸжҙӣи’Ӯйӯ”д№ӢеӯҗжҳҜе•ҘгҖӮеҘ№дёҖи„ёе«Ңејғең°зңӢзқҖдҪ пјҢдјјд№ҺеңЁиҜҙвҖңиҝһиҝҷйғҪдёҚзҹҘйҒ“пјҹвҖқгҖӮеҘ№еҝ«йҖҹең°иҜҙпјҡвҖңйӯ”д№ӢеӯҗжҳҜеҸӨиҖҒе°ҒеҚ°дёӯзҡ„е…ій”®дёҖзҺҜгҖӮдёҠеҸӨж—¶жңҹпјҢйӯ”зҺӢиў«еҮ»иҙҘеҗҺпјҢзІҫзҒөпјҢдәәзұ»пјҢзҹ®дәәпјҢиҝҳжңүдәҡдәәд»¬еҜ№йӯ”зҺӢж–ҪеҠ дәҶејәеӨ§е°ҒеҚ°гҖӮе°Ҷйӯ”зҺӢзҡ„зҒөйӯӮеҲҮеүІжҲҗдәҶж— ж•°е°Ҹд»ҪпјҢиҝҷдәӣзҒөйӯӮдјҡиҝӣе…ҘиҪ®еӣһпјҢйҡҸжңәиҜһз”ҹеңЁдё–з•ҢдёҠгҖӮвҖқ[ж®өиҗҪ]вҖңиҝҷж ·йӯ”зҺӢеҲҶж•Јзҡ„зҒөйӯӮдҫқйҷ„еңЁдёҖдёӘдёӘйӯ”д№Ӣеӯҗиә«дёҠпјҢж— жі•йҮҚж–°иҒҡжӢўпјҢе°ұз»қдёҚеҸҜиғҪеӨҚжҙ»гҖӮз„¶иҖҢпјҢеҪ“дёӢзҹ®дәәе·Із»ҸиЎ°иҗҪпјҢзІҫзҒөе·Із»ҸиҰҶзҒӯпјҢдәҡдәәж—©е°ұжүҖеү©ж— еҮ пјҢйӯ”зҺӢе·Із»Ҹж”¶йӣҶеҲ°дәҶеӨ§йғЁеҲҶиў«еҲҶж•Јзҡ„зҒөйӯӮпјҢеҸӘеү©дёӢдәәзұ»дёӯзҡ„йӯ”д№ӢеӯҗгҖӮвҖң[ж®өиҗҪ]еҘ№жҺҘзқҖиҜҙпјҡвҖңеҸӘиҰҒдёҚж–ӯж”»е…Ӣдәәзұ»зҡ„"
    ]
  }
]